emitter/__init__.py
emitter/py.typed
babichjacob_emitter-0.2.0.dist-info/WHEEL
babichjacob_emitter-0.2.0.dist-info/METADATA
babichjacob_emitter-0.2.0.dist-info/RECORD
